MANIFEST.in
README.md
setup.py
djcms_markdown/__init__.py
djcms_markdown/admin.py
djcms_markdown/cms_plugins.py
djcms_markdown/models.py
djcms_markdown.egg-info/PKG-INFO
djcms_markdown.egg-info/SOURCES.txt
djcms_markdown.egg-info/dependency_links.txt
djcms_markdown.egg-info/not-zip-safe
djcms_markdown.egg-info/requires.txt
djcms_markdown.egg-info/top_level.txt
djcms_markdown/migrations/0001_initial.py
djcms_markdown/migrations/0002_auto_20180404_1950.py
djcms_markdown/migrations/__init__.py
djcms_markdown/templates/.DS_Store
djcms_markdown/templates/djcms_markdown/change_form.html
djcms_markdown/templates/djcms_markdown/markdown.html
djcms_markdown/templatetags/__init__.py
djcms_markdown/templatetags/markdownify.py
tests/__init__.py
tests/settings.py
tests/test_models.py