Metadata-Version: 1.1
Name: djcms-markdown
Version: 0.2.1
Summary: Ghost Markdown Editor for Django CMS
Home-page: https://github.com/CarlosMart626/djcms_markdown
Author: Carlos Martínez
Author-email: carlosmart626@gmail.com
License: MIT License
Keywords: django djangocms markdown ghost
Platform: OS Independent
Classifier: Development Status :: 4 - Beta
Classifier: Environment :: Web Environment
Classifier: Framework :: Django
Classifier: Intended Audience :: Developers
Classifier: License :: OSI Approved :: MIT License
Classifier: Operating System :: OS Independent
Classifier: Programming Language :: Python
Classifier: Topic :: Communications
Classifier: Topic :: Internet :: WWW/HTTP :: Dynamic Content
Classifier: Topic :: Internet :: WWW/HTTP :: Dynamic Content :: Message Boards
Classifier: Programming Language :: Python :: 2.6
Classifier: Programming Language :: Python :: 2.7
Classifier: Programming Language :: Python :: 3.5
Classifier: Programming Language :: Python :: 3.6
